.gitattributes
.gitignore
.gitmodules
.readthedocs.yaml
.travis.yml
CMakeLists.txt
CTestConfig.cmake
CTestCustom.cmake.in
LICENSE
LICENSE.md
MANIFEST.in
README.md
_config.yml
setup.py
teca_config.h.in
CMake/FindCuPy.cmake
CMake/FindLibXLSXWriter.cmake
CMake/FindMPI4Py.cmake
CMake/FindMatplotlib.cmake
CMake/FindNetCDF.cmake
CMake/FindNumPy.cmake
CMake/FindPyTorch.cmake
CMake/FindTcpyPI.cmake
CMake/FindUDUnits.cmake
CMake/teca_app.cmake
CMake/teca_interface_library.cmake
CMake/teca_platform_tests.cpp
CMake/teca_python.cmake
CMake/teca_test.cmake
HAMR/.git
HAMR/.gitignore
HAMR/.readthedocs.yaml
HAMR/CITATION.cff
HAMR/CMakeLists.txt
HAMR/README.md
HAMR/hamr_buffer.cxx
HAMR/hamr_buffer.h
HAMR/hamr_buffer.i
HAMR/hamr_buffer_allocator.cxx
HAMR/hamr_buffer_allocator.h
HAMR/hamr_buffer_allocator.i
HAMR/hamr_buffer_handle.h
HAMR/hamr_buffer_handle.i
HAMR/hamr_buffer_impl.h
HAMR/hamr_buffer_pointer.h
HAMR/hamr_buffer_transfer.h
HAMR/hamr_buffer_transfer.i
HAMR/hamr_buffer_util.h
HAMR/hamr_config.cmake.in
HAMR/hamr_config.h.in
HAMR/hamr_copier_traits.h
HAMR/hamr_cuda_copy.cxx
HAMR/hamr_cuda_copy.h
HAMR/hamr_cuda_copy_async.cxx
HAMR/hamr_cuda_copy_async.h
HAMR/hamr_cuda_copy_async_impl.h
HAMR/hamr_cuda_copy_impl.h
HAMR/hamr_cuda_device.cxx
HAMR/hamr_cuda_device.h
HAMR/hamr_cuda_kernels.h
HAMR/hamr_cuda_launch.cxx
HAMR/hamr_cuda_launch.h
HAMR/hamr_cuda_malloc_allocator.cxx
HAMR/hamr_cuda_malloc_allocator.h
HAMR/hamr_cuda_malloc_allocator_impl.h
HAMR/hamr_cuda_malloc_async_allocator.cxx
HAMR/hamr_cuda_malloc_async_allocator.h
HAMR/hamr_cuda_malloc_async_allocator_impl.h
HAMR/hamr_cuda_malloc_host_allocator.cxx
HAMR/hamr_cuda_malloc_host_allocator.h
HAMR/hamr_cuda_malloc_host_allocator_impl.h
HAMR/hamr_cuda_malloc_uva_allocator.cxx
HAMR/hamr_cuda_malloc_uva_allocator.h
HAMR/hamr_cuda_malloc_uva_allocator_impl.h
HAMR/hamr_cuda_print.cxx
HAMR/hamr_cuda_print.h
HAMR/hamr_cuda_print_impl.h
HAMR/hamr_device.h
HAMR/hamr_env.cxx
HAMR/hamr_env.h
HAMR/hamr_gil_state.h
teca.egg-info/PKG-INFO
teca.egg-info/SOURCES.txt
teca.egg-info/dependency_links.txt
teca.egg-info/not-zip-safe
teca.egg-info/requires.txt
teca.egg-info/top_level.txt
