Metadata-Version: 2.1
Name: teca
Version: 6.0.0
Summary: The Toolkit for Extreme Climate Analysis
Home-page: https://github.com/LBL-EESA/TECA
Author: Burlen Loring
Author-email: bloring@lbl.gov
Classifier: Programming Language :: Python
Classifier: Operating System :: POSIX
Classifier: Operating System :: MacOS
Classifier: License :: Other/Proprietary License
License-File: LICENSE
License-File: LICENSE.md
